lo_dev_search/__init__.py
lo_dev_search/api_data/__init__.py
lo_dev_search/api_data/base_sql.py
lo_dev_search/api_data/db_connect.py
lo_dev_search/api_data/ooo_type.py
lo_dev_search/api_data/qry_component.py
lo_dev_search/api_data/qry_module_info.py
lo_dev_search/api_data/sql_ctx.py
lo_dev_search/api_search/__init__.py
lo_dev_search/api_search/search_api.py
lo_dev_search/cfg/__init__.py
lo_dev_search/cfg/config.json
lo_dev_search/cfg/config.py
lo_dev_search/cli/__init__.py
lo_dev_search/cli/loapi.py
lo_dev_search/cli/lodoc.py
lo_dev_search/cli/loguide.py
lo_dev_search/cli/loproc.py
lo_dev_search/data_class/__init__.py
lo_dev_search/data_class/component.py
lo_dev_search/data_class/module_detail.py
lo_dev_search/data_class/module_info.py
lo_dev_search/db/__init__.py
lo_dev_search/db/mod_info.sqlite
lo_dev_search/utils/__init__.py
lo_dev_search/utils/question.py
lo_dev_search/utils/sys_info.py
lo_dev_search/utils/util.py
lo_dev_search/web_search/__init__.py
lo_dev_search/web_search/browse.py
lo_dev_search/web_search/search_guide.py
lo_dev_search/web_search/search_lo_doc.py
lo_dev_search-2.0.2.dist-info/LICENSE
lo_dev_search-2.0.2.dist-info/METADATA
lo_dev_search-2.0.2.dist-info/WHEEL
lo_dev_search-2.0.2.dist-info/entry_points.txt
lo_dev_search-2.0.2.dist-info/RECORD
