Metadata-Version: 2.1
Name: lo-dev-search
Version: 2.0.2
Summary: LibreOffice Developer Search Engine
Home-page: https://github.com/Amourspirit/python_lo_dev_search
License: MIT
Keywords: libreoffice,openoffice,search,uno,ooouno,pyuno
Author: :Barry-Thomas-Paul: Moss
Author-email: vibrationoflife@protonmail.com
Requires-Python: >=3.7,<4.0
Classifier: Environment :: Other Environment
Classifier: Intended Audience :: Developers
Classifier: License :: OSI Approved :: MIT License
Classifier: Operating System :: OS Independent
Classifier: Programming Language :: Python
Classifier: Programming Language :: Python :: 3
Classifier: Programming Language :: Python :: 3.7
Classifier: Programming Language :: Python :: 3.8
Classifier: Programming Language :: Python :: 3.9
Classifier: Programming Language :: Python :: 3.10
Classifier: Programming Language :: Python :: 3.11
Classifier: Programming Language :: Python :: 3.10
Classifier: Programming Language :: Python :: 3.11
Classifier: Programming Language :: Python :: 3.7
Classifier: Programming Language :: Python :: 3.8
Classifier: Programming Language :: Python :: 3.9
Classifier: Topic :: Office/Business
Requires-Dist: psutil (>=5.8)
Project-URL: Repository, https://github.com/Amourspirit/python_lo_dev_search
